browserbase/__init__.py
browserbase/_base_client.py
browserbase/_client.py
browserbase/_compat.py
browserbase/_constants.py
browserbase/_exceptions.py
browserbase/_files.py
browserbase/_models.py
browserbase/_qs.py
browserbase/_resource.py
browserbase/_response.py
browserbase/_streaming.py
browserbase/_types.py
browserbase/_version.py
browserbase/py.typed
browserbase/_utils/__init__.py
browserbase/_utils/_logs.py
browserbase/_utils/_proxy.py
browserbase/_utils/_reflection.py
browserbase/_utils/_streams.py
browserbase/_utils/_sync.py
browserbase/_utils/_transform.py
browserbase/_utils/_typing.py
browserbase/_utils/_utils.py
browserbase/lib/.keep
browserbase/resources/__init__.py
browserbase/resources/contexts.py
browserbase/resources/extensions.py
browserbase/resources/projects.py
browserbase/resources/sessions/__init__.py
browserbase/resources/sessions/downloads.py
browserbase/resources/sessions/logs.py
browserbase/resources/sessions/recording.py
browserbase/resources/sessions/sessions.py
browserbase/resources/sessions/uploads.py
browserbase/types/__init__.py
browserbase/types/context.py
browserbase/types/context_create_params.py
browserbase/types/context_create_response.py
browserbase/types/context_update_response.py
browserbase/types/extension.py
browserbase/types/extension_create_params.py
browserbase/types/project.py
browserbase/types/project_list_response.py
browserbase/types/project_usage.py
browserbase/types/session.py
browserbase/types/session_create_params.py
browserbase/types/session_create_response.py
browserbase/types/session_list_params.py
browserbase/types/session_list_response.py
browserbase/types/session_live_urls.py
browserbase/types/session_retrieve_response.py
browserbase/types/session_update_params.py
browserbase/types/sessions/__init__.py
browserbase/types/sessions/log_list_response.py
browserbase/types/sessions/recording_retrieve_response.py
browserbase/types/sessions/session_log.py
browserbase/types/sessions/session_recording.py
browserbase-1.3.0.dist-info/METADATA
browserbase-1.3.0.dist-info/WHEEL
browserbase-1.3.0.dist-info/licenses/LICENSE
browserbase-1.3.0.dist-info/RECORD
